README.md
setup.py
pcl/__init__.py
pcl.egg-info/PKG-INFO
pcl.egg-info/SOURCES.txt
pcl.egg-info/dependency_links.txt
pcl.egg-info/top_level.txt