Metadata-Version: 1.0
Name: pcl
Version: 0.0.0.post1
Summary: PCL is a 'python like' language designed for configuration.
Home-page: https://github.com/orcatools/pcl
Author: Dan Sikes
Author-email: dansikes7@gmail.com
License: UNKNOWN
Project-URL: Source, https://github.com/orcatools/pcl
Keywords: python,configuration,python configuration language,pcl
Platform: UNKNOWN
